sol_calc/__init__.py
sol_calc/calc.py
sol_calc-0.2.5.dist-info/METADATA
sol_calc-0.2.5.dist-info/WHEEL
sol_calc-0.2.5.dist-info/entry_points.txt
sol_calc-0.2.5.dist-info/top_level.txt
sol_calc-0.2.5.dist-info/RECORD
