Metadata-Version: 2.1
Name: sol_calc
Version: 0.2.5
Summary: Default template for PDM package
Author-email: j25ng <jsan2861@gmail.com>
License: MIT
Project-URL: Homepage, https://github.com/j25ng/sol_calc
Requires-Python: ==3.11.*
Requires-Dist: sol-add >=0.1.0
Requires-Dist: sol-mul >=0.1.0
Requires-Dist: sol-div >=0.1.0
